{"version": 0.6, "generator": "Overpass API 0.7.62.1 084b4234", "osm3s": {"timestamp_osm_base": "2024-11-11T18:33:21Z", "copyright": "The data included in this document is from www.openstreetmap.org. The data is made available under ODbL."}, "elements": [{"type": "node", "id": 289047986, "lat": 45.0594042, "lon": 7.6147164}, {"type": "node", "id": 289048006, "lat": 45.057274, "lon": 7.6147971}, {"type": "node", "id": 291981313, "lat": 45.0532215, "lon": 7.6155253}, {"type": "node", "id": 291981315, "lat": 45.0590579, "lon": 7.6152128}, {"type": "node", "id": 291981317, "lat": 45.0592605, "lon": 7.6153801}, {"type": "node", "id": 291981319, "lat": 45.059325, "lon": 7.6153725}, {"type": "node", "id": 291981320, "lat": 45.0595181, "lon": 7.6151067}, {"type": "node", "id": 291981322, "lat": 45.0594663, "lon": 7.6147922}, {"type": "node", "id": 291981323, "lat": 45.0592464, "lon": 7.6146657}, {"type": "node", "id": 291981325, "lat": 45.0590713, "lon": 7.614804}, {"type": "node", "id": 291981327, "lat": 45.0596382, "lon": 7.6137255}, {"type": "node", "id": 446193210, "lat": 45.0528951, "lon": 7.6179796}, {"type": "node", "id": 452435004, "lat": 45.0599291, "lon": 7.6115026}, {"type": "node", "id": 473708950, "lat": 45.0554223, "lon": 7.6148788}, {"type": "node", "id": 473708976, "lat": 45.0591488, "lon": 7.6147092}, {"type": "node", "id": 475832672, "lat": 45.0549219, "lon": 7.6098615}, {"type": "node", "id": 475832793, "lat": 45.0577527, "lon": 7.6070141}, {"type": "node", "id": 475832795, "lat": 45.0572289, "lon": 7.6094405}, {"type": "node", "id": 475832796, "lat": 45.0570943, "lon": 7.610143}, {"type": "node", "id": 475832798, "lat": 45.0569463, "lon": 7.6108528}, {"type": "node", "id": 480309865, "lat": 45.0588472, "lon": 7.6201629}, {"type": "node", "id": 480309868, "lat": 45.0594111, "lon": 7.6160092}, {"type": "node", "id": 480309871, "lat": 45.0553296, "lon": 7.6242986}, {"type": "node", "id": 480309873, "lat": 45.0564125, "lon": 7.6191718}, {"type": "node", "id": 480309874, "lat": 45.0563972, "lon": 7.6192944}, {"type": "node", "id": 480309875, "lat": 45.0588113, "lon": 7.6202806}, {"type": "node", "id": 480309877, "lat": 45.0555172, "lon": 7.6234083, "tags": {"traffic_calming": "table"}}, {"type": "node", "id": 480309880, "lat": 45.0557006, "lon": 7.6225493, "tags": {"traffic_calming": "table"}}, {"type": "node", "id": 480309883, "lat": 45.0558835, "lon": 7.6216957}, {"type": "node", "id": 480309890, "lat": 45.0547446, "lon": 7.6185096}, {"type": "node", "id": 480309894, "lat": 45.0572074, "lon": 7.6209153, "tags": {"noexit": "yes"}}, {"type": "node", "id": 480309895, "lat": 45.056919, "lon": 7.6221387}, {"type": "node", "id": 480309897, "lat": 45.0567366, "lon": 7.6229978}, {"type": "node", "id": 480309898, "lat": 45.0565539, "lon": 7.6238475}, {"type": "node", "id": 480309900, "lat": 45.0563649, "lon": 7.6247189}, {"type": "node", "id": 480309906, "lat": 45.0592876, "lon": 7.6170705}, {"type": "node", "id": 480309908, "lat": 45.0590344, "lon": 7.6148991}, {"type": "node", "id": 480309909, "lat": 45.0591114, "lon": 7.6152989}, {"type": "node", "id": 480309911, "lat": 45.0594568, "lon": 7.6152801}, {"type": "node", "id": 480309912, "lat": 45.0595119, "lon": 7.6149175}, {"type": "node", "id": 480309914, "lat": 45.0593196, "lon": 7.6154398}, {"type": "node", "id": 480309915, "lat": 45.059331, "lon": 7.6145593}, {"type": "node", "id": 480309917, "lat": 45.0584854, "lon": 7.6152943}, {"type": "node", "id": 480309919, "lat": 45.0585582, "lon": 7.6152297}, {"type": "node", "id": 480309920, "lat": 45.0586211, "lon": 7.6151691}, {"type": "node", "id": 480309922, "lat": 45.0586567, "lon": 7.6150667}, {"type": "node", "id": 480309924, "lat": 45.0586608, "lon": 7.6149877}, {"type": "node", "id": 480309926, "lat": 45.0586286, "lon": 7.6148697}, {"type": "node", "id": 480309927, "lat": 45.0585988, "lon": 7.6148192}, {"type": "node", "id": 480309929, "lat": 45.0585234, "lon": 7.6147217}, {"type": "node", "id": 480309933, "lat": 45.0562624, "lon": 7.6205859}, {"type": "node", "id": 480309935, "lat": 45.0565277, "lon": 7.619351}, {"type": "node", "id": 480309938, "lat": 45.0560752, "lon": 7.620801}, {"type": "node", "id": 480309940, "lat": 45.0585141, "lon": 7.6201645}, {"type": "node", "id": 480309941, "lat": 45.0584561, "lon": 7.6212962}, {"type": "node", "id": 534251216, "lat": 45.0575656, "lon": 7.6078694}, {"type": "node", "id": 534251218, "lat": 45.059055, "lon": 7.6075866}, {"type": "node", "id": 534251219, "lat": 45.0588753, "lon": 7.6084044}, {"type": "node", "id": 541515106, "lat": 45.0656172, "lon": 7.6170185}, {"type": "node", "id": 541515108, "lat": 45.0616327, "lon": 7.6159843}, {"type": "node", "id": 541516394, "lat": 45.0603423, "lon": 7.6205784}, {"type": "node", "id": 541516400, "lat": 45.0608346, "lon": 7.6206231}, {"type": "node", "id": 541530839, "lat": 45.0594862, "lon": 7.6204611}, {"type": "node", "id": 541541115, "lat": 45.0594247, "lon": 7.6229155}, {"type": "node", "id": 541541120, "lat": 45.0596572, "lon": 7.6250917}, {"type": "node", "id": 541541124, "lat": 45.0597387, "lon": 7.6270457}, {"type": "node", "id": 541541129, "lat": 45.0598155, "lon": 7.627239}, {"type": "node", "id": 558294551, "lat": 45.0634023, "lon": 7.6164437}, {"type": "node", "id": 558304678, "lat": 45.0627226, "lon": 7.6206787}, {"type": "node", "id": 558304694, "lat": 45.0610044, "lon": 7.6198772}, {"type": "node", "id": 741081228, "lat": 45.0593821, "lon": 7.6221312}, {"type": "node", "id": 741081242, "lat": 45.0595641, "lon": 7.6241424}, {"type": "node", "id": 802216522, "lat": 45.05706, "lon": 7.610322}, {"type": "node", "id": 802216525, "lat": 45.0550383, "lon": 7.6093394, "tags": {"crossing": "marked", "highway": "crossing"}}, {"type": "node", "id": 802216531, "lat": 45.0549625, "lon": 7.6093129}, {"type": "node", "id": 950728322, "lat": 45.0593859, "lon": 7.6156657}, {"type": "node", "id": 950728371, "lat": 45.0590193, "lon": 7.6150054}, {"type": "node", "id": 950728386, "lat": 45.0594888, "lon": 7.6152073}, {"type": "node", "id": 950728418, "lat": 45.0594331, "lon": 7.6154457}, {"type": "node", "id": 950728423, "lat": 45.0595168, "lon": 7.6146196}, {"type": "node", "id": 950728438, "lat": 45.0594638, "lon": 7.6156766}, {"type": "node", "id": 950728470, "lat": 45.0593282, "lon": 7.6146727}, {"type": "node", "id": 954620513, "lat": 45.063024, "lon": 7.6188348}, {"type": "node", "id": 954620516, "lat": 45.0646305, "lon": 7.6195208}, {"type": "node", "id": 958410758, "lat": 45.0625777, "lon": 7.6175211}, {"type": "node", "id": 958410762, "lat": 45.0628033, "lon": 7.6162859}, {"type": "node", "id": 958410769, "lat": 45.0618697, "lon": 7.6202676}, {"type": "node", "id": 958410780, "lat": 45.061438, "lon": 7.6171614}, {"type": "node", "id": 958410782, "lat": 45.0593603, "lon": 7.6206326}, {"type": "node", "id": 958410784, "lat": 45.0593945, "lon": 7.6204882}, {"type": "node", "id": 958410785, "lat": 45.0623534, "lon": 7.6174542}, {"type": "node", "id": 968066859, "lat": 45.0562197, "lon": 7.6148961}, {"type": "node", "id": 968066884, "lat": 45.0561328, "lon": 7.6151346}, {"type": "node", "id": 968066887, "lat": 45.0538303, "lon": 7.6154868}, {"type": "node", "id": 968066889, "lat": 45.0563835, "lon": 7.6148364}, {"type": "node", "id": 968066893, "lat": 45.0560377, "lon": 7.6152285}, {"type": "node", "id": 968066899, "lat": 45.0562537, "lon": 7.6153041}, {"type": "node", "id": 968066903, "lat": 45.0554661, "lon": 7.6154192}, {"type": "node", "id": 968066907, "lat": 45.054679, "lon": 7.6149132}, {"type": "node", "id": 968066910, "lat": 45.0560269, "lon": 7.6149726}, {"type": "node", "id": 968066916, "lat": 45.0559678, "lon": 7.6153102}, {"type": "node", "id": 968066921, "lat": 45.0558692, "lon": 7.6148613}, {"type": "node", "id": 968066932, "lat": 45.0561603, "lon": 7.6149619}, {"type": "node", "id": 968066949, "lat": 45.0561711, "lon": 7.6152394}, {"type": "node", "id": 968066960, "lat": 45.0560644, "lon": 7.6151299}, {"type": "node", "id": 968066966, "lat": 45.0563936, "lon": 7.6153647}, {"type": "node", "id": 968066977, "lat": 45.05595, "lon": 7.614903, "tags": {"direction": "forward", "highway": "give_way"}}, {"type": "node", "id": 968066995, "lat": 45.0558639, "lon": 7.6153941}, {"type": "node", "id": 968066996, "lat": 45.0566882, "lon": 7.6153543}, {"type": "node", "id": 968139241, "lat": 45.0581149, "lon": 7.6071762}, {"type": "node", "id": 968139361, "lat": 45.0594863, "lon": 7.6142369}, {"type": "node", "id": 1194057653, "lat": 45.0579129, "lon": 7.6147576}, {"type": "node", "id": 1194126701, "lat": 45.0551553, "lon": 7.6099799}, {"type": "node", "id": 1270518252, "lat": 45.0588776, "lon": 7.6147694, "tags": {"crossing": "marked", "highway": "crossing"}}, {"type": "node", "id": 1270518263, "lat": 45.0593826, "lon": 7.6144778, "tags": {"crossing": "uncontrolled", "highway": "crossing"}}, {"type": "node", "id": 1270518269, "lat": 45.0588918, "lon": 7.6152272, "tags": {"crossing": "marked", "highway": "crossing"}}, {"type": "node", "id": 1270518270, "lat": 45.0587753, "lon": 7.6203931, "tags": {"crossing": "traffic_signals", "highway": "crossing"}}, {"type": "node", "id": 1270518277, "lat": 45.0587424, "lon": 7.6201179, "tags": {"button_operated": "no", "crossing": "traffic_signals", "crossing:island": "no", "highway": "crossing", "tactile_paving": "no", "traffic_signals:sound": "no", "traffic_signals:vibration": "no"}}, {"type": "node", "id": 1270518298, "lat": 45.0529341, "lon": 7.6179905, "tags": {"crossing": "marked", "crossing:island": "no", "crossing:markings": "yes", "highway": "crossing", "tactile_paving": "no"}}, {"type": "node", "id": 1270518308, "lat": 45.0591813, "lon": 7.6153566}, {"type": "node", "id": 1270518311, "lat": 45.0595316, "lon": 7.6145339, "tags": {"crossing": "uncontrolled", "highway": "crossing"}}, {"type": "node", "id": 1270518312, "lat": 45.0587052, "lon": 7.6202308, "tags": {"button_operated": "no", "crossing": "traffic_signals", "highway": "crossing", "tactile_paving": "no", "traffic_signals:sound": "no", "traffic_signals:vibration": "no"}}, {"type": "node", "id": 1436708412, "lat": 45.0582515, "lon": 7.6200603}, {"type": "node", "id": 1478247973, "lat": 45.0591067, "lon": 7.614751}, {"type": "node", "id": 1478247990, "lat": 45.059196, "lon": 7.6146804}, {"type": "node", "id": 1493709560, "lat": 45.060222, "lon": 7.608961, "tags": {"crossing": "uncontrolled", "highway": "crossing"}}, {"type": "node", "id": 1627688857, "lat": 45.0595847, "lon": 7.6243356}, {"type": "node", "id": 1627688858, "lat": 45.0631828, "lon": 7.6130777}, {"type": "node", "id": 1627688859, "lat": 45.0594986, "lon": 7.6236127}, {"type": "node", "id": 1627688864, "lat": 45.0630638, "lon": 7.6139223}, {"type": "node", "id": 1627688876, "lat": 45.0648977, "lon": 7.6144897}, {"type": "node", "id": 1631841304, "lat": 45.0607872, "lon": 7.6207234, "tags": {"crossing": "marked", "highway": "crossing"}}, {"type": "node", "id": 1668523677, "lat": 45.0566165, "lon": 7.6101065}, {"type": "node", "id": 1668523680, "lat": 45.0596704, "lon": 7.6134795}, {"type": "node", "id": 1668523683, "lat": 45.0598668, "lon": 7.6119766}, {"type": "node", "id": 1842990922, "lat": 45.0603108, "lon": 7.6090002}, {"type": "node", "id": 1849617217, "lat": 45.0601273, "lon": 7.6101004}, {"type": "node", "id": 2016906738, "lat": 45.0593707, "lon": 7.6217609}, {"type": "node", "id": 2016906740, "lat": 45.0587797, "lon": 7.6216493}, {"type": "node", "id": 2318240816, "lat": 45.0606112, "lon": 7.6218566}, {"type": "node", "id": 2318240818, "lat": 45.0608853, "lon": 7.620546, "tags": {"crossing": "marked", "highway": "crossing"}}, {"type": "node", "id": 2318240819, "lat": 45.0609355, "lon": 7.6206486, "tags": {"crossing": "marked", "highway": "crossing"}}, {"type": "node", "id": 2856450889, "lat": 45.059611, "lon": 7.6140494}, {"type": "node", "id": 2856450890, "lat": 45.0595563, "lon": 7.6140049}, {"type": "node", "id": 2856453137, "lat": 45.0594609, "lon": 7.6158532}, {"type": "node", "id": 2856453138, "lat": 45.0593943, "lon": 7.6158421}, {"type": "node", "id": 2856453139, "lat": 45.0593657, "lon": 7.615532}, {"type": "node", "id": 2856453140, "lat": 45.0588986, "lon": 7.6199779, "tags": {"highway": "traffic_signals", "traffic_signals": "signal", "traffic_signals:direction": "forward"}}, {"type": "node", "id": 2879618070, "lat": 45.0603844, "lon": 7.6081221, "tags": {"crossing": "uncontrolled", "highway": "crossing"}}, {"type": "node", "id": 3088265531, "lat": 45.0595247, "lon": 7.6149983}, {"type": "node", "id": 3088265532, "lat": 45.0590274, "lon": 7.6151133}, {"type": "node", "id": 3088265533, "lat": 45.059386, "lon": 7.6153421}, {"type": "node", "id": 3088265534, "lat": 45.0584207, "lon": 7.6152964}, {"type": "node", "id": 3088265535, "lat": 45.058401, "lon": 7.6147289}, {"type": "node", "id": 4160817555, "lat": 45.0614266, "lon": 7.6172309, "tags": {"crossing": "zebra", "highway": "crossing"}}, {"type": "node", "id": 4160817556, "lat": 45.061501, "lon": 7.6171819, "tags": {"crossing": "zebra", "highway": "crossing"}}, {"type": "node", "id": 4160817559, "lat": 45.0610211, "lon": 7.6197727, "tags": {"crossing": "zebra", "highway": "crossing"}}, {"type": "node", "id": 4160817560, "lat": 45.0610749, "lon": 7.6199048, "tags": {"crossing": "zebra", "highway": "crossing"}}, {"type": "node", "id": 4353790038, "lat": 45.0601779, "lon": 7.6097754}, {"type": "node", "id": 4353790039, "lat": 45.0604718, "lon": 7.6081646}, {"type": "node", "id": 4353790054, "lat": 45.0589654, "lon": 7.6197171}, {"type": "node", "id": 4362729375, "lat": 45.0590852, "lon": 7.6187881}, {"type": "node", "id": 4914464895, "lat": 45.0603066, "lon": 7.6080908}, {"type": "node", "id": 5726776747, "lat": 45.0597304, "lon": 7.626875, "tags": {"crossing": "traffic_signals", "highway": "crossing"}}, {"type": "node", "id": 5726776748, "lat": 45.0597279, "lon": 7.6268314, "tags": {"highway": "traffic_signals", "traffic_signals": "signal", "traffic_signals:direction": "forward"}}, {"type": "node", "id": 6297083386, "lat": 45.0536882, "lon": 7.6182028, "tags": {"crossing": "marked", "crossing:island": "no", "crossing:markings": "yes", "highway": "crossing", "tactile_paving": "no"}}, {"type": "node", "id": 6297083388, "lat": 45.0565138, "lon": 7.6194153, "tags": {"direction": "forward", "highway": "stop"}}, {"type": "node", "id": 6297083390, "lat": 45.0587588, "lon": 7.6204405, "tags": {"highway": "traffic_signals", "traffic_signals": "signal", "traffic_signals:direction": "backward"}}, {"type": "node", "id": 6297083391, "lat": 45.0586642, "lon": 7.6202147, "tags": {"highway": "traffic_signals", "traffic_signals": "signal", "traffic_signals:direction": "forward"}}, {"type": "node", "id": 6297083392, "lat": 45.0587034, "lon": 7.620102, "tags": {"highway": "traffic_signals", "traffic_signals": "signal", "traffic_signals:direction": "backward"}}, {"type": "node", "id": 6297087353, "lat": 45.0590231, "lon": 7.6193283}, {"type": "node", "id": 6297087354, "lat": 45.0589952, "lon": 7.6195476}, {"type": "node", "id": 6297087355, "lat": 45.0589388, "lon": 7.6198413}, {"type": "node", "id": 6315013294, "lat": 45.0533242, "lon": 7.6155188, "tags": {"button_operated": "no", "crossing": "traffic_signals", "highway": "crossing", "tactile_paving": "no", "traffic_signals:sound": "no", "traffic_signals:vibration": "no"}}, {"type": "node", "id": 6393899001, "lat": 45.0558624, "lon": 7.6189534}, {"type": "node", "id": 6393899006, "lat": 45.0574748, "lon": 7.6196027}, {"type": "node", "id": 6438403802, "lat": 45.0613225, "lon": 7.6178712}, {"type": "node", "id": 6438403803, "lat": 45.0610209, "lon": 7.6177701}, {"type": "node", "id": 6438403804, "lat": 45.0608263, "lon": 7.6177179}, {"type": "node", "id": 7105685473, "lat": 45.065552, "lon": 7.6170005, "tags": {"crossing": "marked", "crossing:markings": "yes", "highway": "crossing"}}, {"type": "node", "id": 7105685475, "lat": 45.0645422, "lon": 7.6194831, "tags": {"crossing": "marked", "crossing:island": "no", "crossing:markings": "yes", "highway": "crossing", "tactile_paving": "no"}}, {"type": "node", "id": 7724324783, "lat": 45.0620286, "lon": 7.6173477}, {"type": "node", "id": 7724324784, "lat": 45.0622251, "lon": 7.6161337}, {"type": "node", "id": 7940000003, "lat": 45.0566891, "lon": 7.6194168, "tags": {"crossing": "marked", "crossing:markings": "yes", "highway": "crossing"}}, {"type": "node", "id": 8040903287, "lat": 45.0546741, "lon": 7.6184811, "tags": {"crossing": "marked", "crossing:island": "no", "crossing:markings": "yes", "highway": "crossing", "tactile_paving": "no"}}, {"type": "node", "id": 8040903288, "lat": 45.056508, "lon": 7.6194418, "tags": {"crossing": "marked", "crossing:markings": "yes", "highway": "crossing", "tactile_paving": "no"}}, {"type": "node", "id": 8040903289, "lat": 45.0563743, "lon": 7.6193922, "tags": {"crossing": "marked", "crossing:island": "no", "crossing:markings": "yes", "highway": "crossing", "tactile_paving": "no"}}, {"type": "node", "id": 8040903290, "lat": 45.0554795, "lon": 7.6235914, "tags": {"crossing": "marked", "crossing:markings": "yes", "highway": "crossing"}}, {"type": "node", "id": 8040903293, "lat": 45.0564012, "lon": 7.6245532, "tags": {"crossing": "marked", "crossing:markings": "yes", "highway": "crossing"}}, {"type": "node", "id": 8040903295, "lat": 45.0565754, "lon": 7.6237454, "tags": {"crossing": "marked", "crossing:markings": "yes", "highway": "crossing"}}, {"type": "node", "id": 8040903296, "lat": 45.0553729, "lon": 7.6240981, "tags": {"crossing": "marked", "crossing:markings": "yes", "highway": "crossing"}}, {"type": "node", "id": 8040903298, "lat": 45.0567583, "lon": 7.6228902, "tags": {"crossing": "marked", "crossing:markings": "yes", "highway": "crossing"}}, {"type": "node", "id": 8040903300, "lat": 45.0567155, "lon": 7.6231002, "tags": {"crossing": "marked", "crossing:markings": "yes", "highway": "crossing"}}, {"type": "node", "id": 8040903301, "lat": 45.0568968, "lon": 7.6222491, "tags": {"crossing": "marked", "crossing:markings": "yes", "highway": "crossing"}}, {"type": "node", "id": 8040903302, "lat": 45.0569392, "lon": 7.6220346, "tags": {"crossing": "marked", "crossing:markings": "yes", "highway": "crossing"}}, {"type": "node", "id": 8040903310, "lat": 45.056321, "lon": 7.6191348, "tags": {"crossing": "marked", "crossing:island": "no", "crossing:markings": "yes", "highway": "crossing", "tactile_paving": "no"}}, {"type": "node", "id": 8040903311, "lat": 45.0550572, "lon": 7.6154361, "tags": {"crossing": "marked", "highway": "crossing", "traffic_calming": "table"}}, {"type": "node", "id": 8040903312, "lat": 45.0550388, "lon": 7.6148963, "tags": {"crossing": "marked", "highway": "crossing", "tactile_paving": "no", "traffic_calming": "table"}}, {"type": "node", "id": 8040903316, "lat": 45.0569942, "lon": 7.6148094, "tags": {"crossing": "marked", "highway": "crossing"}}, {"type": "node", "id": 8040903317, "lat": 45.0570104, "lon": 7.6153435, "tags": {"crossing": "marked", "highway": "crossing"}}, {"type": "node", "id": 8059293110, "lat": 45.0650502, "lon": 7.6144917}, {"type": "node", "id": 8066692022, "lat": 45.0574113, "lon": 7.6197091, "tags": {"crossing": "marked", "highway": "crossing", "tactile_paving": "no"}}, {"type": "node", "id": 8072412140, "lat": 45.059661, "lon": 7.6251725, "tags": {"crossing": "marked", "crossing:markings": "yes", "highway": "crossing"}}, {"type": "node", "id": 8072412144, "lat": 45.0594354, "lon": 7.6204643, "tags": {"crossing": "marked", "highway": "crossing"}}, {"type": "node", "id": 8072412146, "lat": 45.0625324, "lon": 7.6214065, "tags": {"crossing": "marked", "crossing:markings": "yes", "highway": "crossing"}}, {"type": "node", "id": 8072412147, "lat": 45.0627381, "lon": 7.6205581, "tags": {"crossing": "marked", "crossing:markings": "yes", "highway": "crossing"}}, {"type": "node", "id": 8072412149, "lat": 45.0626505, "lon": 7.6206406, "tags": {"crossing": "marked", "crossing:markings": "yes", "highway": "crossing"}}, {"type": "node", "id": 8072412150, "lat": 45.0630759, "lon": 7.6188568, "tags": {"crossing": "marked", "crossing:markings": "yes", "highway": "crossing"}}, {"type": "node", "id": 8072412151, "lat": 45.0633923, "lon": 7.6165201, "tags": {"crossing": "marked", "highway": "crossing"}}, {"type": "node", "id": 8072412152, "lat": 45.0622091, "lon": 7.6162358, "tags": {"crossing": "marked", "highway": "crossing"}}, {"type": "node", "id": 8072412153, "lat": 45.0623408, "lon": 7.6175305, "tags": {"crossing": "marked", "highway": "crossing"}}, {"type": "node", "id": 8072412154, "lat": 45.0624629, "lon": 7.6174868, "tags": {"crossing": "marked", "highway": "crossing"}}, {"type": "node", "id": 8072412155, "lat": 45.0620453, "lon": 7.6172572, "tags": {"crossing": "marked", "highway": "crossing"}}, {"type": "node", "id": 8072412156, "lat": 45.0627898, "lon": 7.6163743, "tags": {"crossing": "marked", "highway": "crossing"}}, {"type": "node", "id": 8072412157, "lat": 45.0618842, "lon": 7.6201803, "tags": {"crossing": "marked", "highway": "crossing"}}, {"type": "node", "id": 8137404136, "lat": 45.0647754, "lon": 7.6167941}, {"type": "node", "id": 8375944293, "lat": 45.0649978, "lon": 7.6144872, "tags": {"bicycle": "yes", "crossing": "marked", "crossing:island": "no", "crossing_ref": "zebra", "highway": "crossing"}}, {"type": "node", "id": 8942485659, "lat": 45.0560104, "lon": 7.6152691}, {"type": "node", "id": 8942485660, "lat": 45.0560563, "lon": 7.6151819}, {"type": "node", "id": 8942485661, "lat": 45.0560614, "lon": 7.6150692}, {"type": "node", "id": 8942485662, "lat": 45.0560476, "lon": 7.6150166}, {"type": "node", "id": 8942485663, "lat": 45.0559938, "lon": 7.6149335}, {"type": "node", "id": 8942485664, "lat": 45.0561886, "lon": 7.6149233}, {"type": "node", "id": 8942485665, "lat": 45.0561405, "lon": 7.6150179}, {"type": "node", "id": 8942485666, "lat": 45.0561306, "lon": 7.6150762}, {"type": "node", "id": 8942485667, "lat": 45.0561455, "lon": 7.6151889}, {"type": "node", "id": 8942485668, "lat": 45.056208, "lon": 7.615281, "tags": {"direction": "forward", "highway": "give_way"}}, {"type": "node", "id": 8942485669, "lat": 45.0585936, "lon": 7.6152068}, {"type": "node", "id": 8942485670, "lat": 45.0586437, "lon": 7.6151219}, {"type": "node", "id": 8942485671, "lat": 45.0586513, "lon": 7.6149256}, {"type": "node", "id": 8942485672, "lat": 45.0585593, "lon": 7.6147833}, {"type": "node", "id": 8942485673, "lat": 45.0585796, "lon": 7.6148018, "tags": {"direction": "forward", "highway": "give_way"}}, {"type": "node", "id": 8942485674, "lat": 45.0576935, "lon": 7.6147712, "tags": {"crossing": "marked", "highway": "crossing", "tactile_paving": "no"}}, {"type": "node", "id": 8942485687, "lat": 45.0568173, "lon": 7.6148172}, {"type": "node", "id": 8942625422, "lat": 45.0550084, "lon": 7.6099054, "tags": {"crossing": "marked", "highway": "crossing"}}, {"type": "node", "id": 8942625423, "lat": 45.0570238, "lon": 7.6103044, "tags": {"direction": "forward", "highway": "stop"}}, {"type": "node", "id": 8942625424, "lat": 45.0570342, "lon": 7.6104424, "tags": {"crossing": "marked", "highway": "crossing"}}, {"type": "node", "id": 9288504122, "lat": 45.0550148, "lon": 7.6093312}, {"type": "node", "id": 9580741275, "lat": 45.0643094, "lon": 7.6142846}, {"type": "node", "id": 10137579535, "lat": 45.062599, "lon": 7.6214377, "tags": {"railway": "tram_level_crossing"}}, {"type": "node", "id": 10152582758, "lat": 45.0644992, "lon": 7.6143916}, {"type": "node", "id": 10229303054, "lat": 45.0563857, "lon": 7.624624, "tags": {"direction": "forward", "highway": "give_way"}}, {"type": "node", "id": 10229303056, "lat": 45.0565312, "lon": 7.6239527, "tags": {"crossing": "marked", "crossing:markings": "yes", "highway": "crossing"}}, {"type": "node", "id": 10229303057, "lat": 45.0565445, "lon": 7.6238912, "tags": {"direction": "backward", "highway": "stop"}}, {"type": "node", "id": 10229303058, "lat": 45.056563, "lon": 7.6238045, "tags": {"direction": "forward", "highway": "stop"}}, {"type": "node", "id": 10229303059, "lat": 45.0567284, "lon": 7.6230375, "tags": {"direction": "backward", "highway": "stop"}}, {"type": "node", "id": 10229303060, "lat": 45.0567454, "lon": 7.6229538, "tags": {"direction": "forward", "highway": "stop"}}, {"type": "node", "id": 10229303061, "lat": 45.056927, "lon": 7.6220972, "tags": {"direction": "forward", "highway": "stop"}}, {"type": "node", "id": 10229303062, "lat": 45.05691, "lon": 7.6221835, "tags": {"direction": "backward", "highway": "stop"}}, {"type": "node", "id": 10229303064, "lat": 45.0559038, "lon": 7.6215978, "tags": {"crossing": "marked", "crossing:markings": "yes", "highway": "crossing"}}, {"type": "node", "id": 10229303065, "lat": 45.0558618, "lon": 7.6217961, "tags": {"crossing": "marked", "crossing:markings": "yes", "highway": "crossing"}}, {"type": "node", "id": 10229303067, "lat": 45.0560566, "lon": 7.6208875, "tags": {"crossing": "marked", "crossing:markings": "yes", "highway": "crossing", "traffic_calming": "table"}}, {"type": "node", "id": 10229303068, "lat": 45.0562403, "lon": 7.6206498}, {"type": "node", "id": 10229303069, "lat": 45.0562052, "lon": 7.620701}, {"type": "node", "id": 10229303071, "lat": 45.0556802, "lon": 7.6226453, "tags": {"crossing": "marked", "crossing:markings": "yes", "highway": "crossing"}}, {"type": "node", "id": 10229303075, "lat": 45.0553501, "lon": 7.6242036, "tags": {"direction": "backward", "highway": "give_way"}}, {"type": "node", "id": 10229303076, "lat": 45.054866, "lon": 7.6185578, "tags": {"crossing": "marked", "crossing:island": "no", "crossing:markings": "yes", "highway": "crossing", "tactile_paving": "no"}}, {"type": "node", "id": 10229345821, "lat": 45.0593734, "lon": 7.6205447}, {"type": "node", "id": 10229345827, "lat": 45.0609105, "lon": 7.6204629}, {"type": "node", "id": 10229345828, "lat": 45.0607987, "lon": 7.6206884}, {"type": "node", "id": 10229345829, "lat": 45.0626094, "lon": 7.6174812}, {"type": "node", "id": 10229345830, "lat": 45.0625978, "lon": 7.6175109}, {"type": "node", "id": 10229345831, "lat": 45.0631789, "lon": 7.6178614, "tags": {"traffic_calming": "bump"}}, {"type": "node", "id": 10229345832, "lat": 45.0631159, "lon": 7.6182575, "tags": {"traffic_calming": "bump"}}, {"type": "node", "id": 10229345833, "lat": 45.065571, "lon": 7.6170057, "tags": {"direction": "backward", "highway": "give_way"}}, {"type": "node", "id": 10229345836, "lat": 45.0606186, "lon": 7.6217542}, {"type": "node", "id": 10271830480, "lat": 45.0566217, "lon": 7.6192544}, {"type": "node", "id": 10271830481, "lat": 45.0565412, "lon": 7.6192235, "tags": {"direction": "forward", "highway": "stop"}}, {"type": "node", "id": 10271830492, "lat": 45.0563861, "lon": 7.6191613, "tags": {"direction": "backward", "highway": "stop"}}, {"type": "node", "id": 10271874911, "lat": 45.0557335, "lon": 7.6189022}, {"type": "node", "id": 10271874914, "lat": 45.0570433, "lon": 7.6195553}, {"type": "node", "id": 10271874915, "lat": 45.0570688, "lon": 7.6194369}, {"type": "node", "id": 10271874940, "lat": 45.0574364, "lon": 7.619587, "tags": {"crossing": "marked", "crossing:island": "no", "highway": "crossing", "tactile_paving": "no"}}, {"type": "node", "id": 10271874942, "lat": 45.0567143, "lon": 7.6192924, "tags": {"crossing": "marked", "crossing:markings": "yes", "highway": "crossing"}}, {"type": "node", "id": 11633780516, "lat": 45.0594071, "lon": 7.6160434}, {"type": "node", "id": 11897183146, "lat": 45.0640207, "lon": 7.6192604}, {"type": "node", "id": 11897183149, "lat": 45.064483, "lon": 7.6194578}, {"type": "node", "id": 11897185463, "lat": 45.0630004, "lon": 7.6189771}, {"type": "node", "id": 11897185464, "lat": 45.0621433, "lon": 7.6186768}, {"type": "node", "id": 11897188944, "lat": 45.0610927, "lon": 7.6193208}, {"type": "node", "id": 11897188947, "lat": 45.0610699, "lon": 7.6194648}, {"type": "node", "id": 12110259110, "lat": 45.0645638, "lon": 7.6194923, "tags": {"direction": "backward", "highway": "give_way"}}, {"type": "node", "id": 12111135768, "lat": 45.0605569, "lon": 7.6077153}, {"type": "node", "id": 12111135773, "lat": 45.0604363, "lon": 7.6083605}, {"type": "node", "id": 12111135774, "lat": 45.0603765, "lon": 7.6086623}, {"type": "node", "id": 12111135775, "lat": 45.0602603, "lon": 7.6089751, "tags": {"highway": "stop"}}, {"type": "node", "id": 12111135776, "lat": 45.0592905, "lon": 7.6146097, "tags": {"direction": "forward", "highway": "give_way"}}, {"type": "node", "id": 12111135777, "lat": 45.059503, "lon": 7.6147396}, {"type": "node", "id": 12111135778, "lat": 45.0594907, "lon": 7.6148526}, {"type": "node", "id": 12111135779, "lat": 45.0594367, "lon": 7.6147494}, {"type": "node", "id": 12111135780, "lat": 45.0593658, "lon": 7.6146913}, {"type": "node", "id": 12111135781, "lat": 45.0595887, "lon": 7.6138767}, {"type": "node", "id": 12111135782, "lat": 45.0596352, "lon": 7.6138972}, {"type": "node", "id": 12111135783, "lat": 45.0590149, "lon": 7.6152068, "tags": {"direction": "forward", "highway": "give_way"}}, {"type": "node", "id": 12111135784, "lat": 45.0592226, "lon": 7.6153752}, {"type": "node", "id": 12111135785, "lat": 45.0594346, "lon": 7.6153565, "tags": {"direction": "forward", "highway": "give_way"}}, {"type": "node", "id": 12111135786, "lat": 45.0594497, "lon": 7.6155585}, {"type": "node", "id": 12111135787, "lat": 45.0593465, "lon": 7.6154814}, {"type": "node", "id": 12111135788, "lat": 45.0593784, "lon": 7.6155993}, {"type": "node", "id": 12111135789, "lat": 45.0593977, "lon": 7.6158759}, {"type": "node", "id": 12111135790, "lat": 45.0594085, "lon": 7.6160316}, {"type": "node", "id": 12111135791, "lat": 45.0590227, "lon": 7.6150497}, {"type": "node", "id": 12111135792, "lat": 45.0594949, "lon": 7.6151865}, {"type": "node", "id": 12111135794, "lat": 45.0580846, "lon": 7.6223644}, {"type": "node", "id": 12139007042, "lat": 45.0557456, "lon": 7.6148661}, {"type": "node", "id": 12139007044, "lat": 45.0548081, "lon": 7.6149071}, {"type": "node", "id": 12139007045, "lat": 45.0571692, "lon": 7.6148017}, {"type": "node", "id": 12139007046, "lat": 45.0569423, "lon": 7.6148117}, {"type": "node", "id": 12139007047, "lat": 45.0551673, "lon": 7.6148904}, {"type": "node", "id": 12139007048, "lat": 45.0550494, "lon": 7.6148958}, {"type": "node", "id": 12139007049, "lat": 45.0552768, "lon": 7.615427}, {"type": "node", "id": 12139007052, "lat": 45.0568564, "lon": 7.6153487}, {"type": "node", "id": 12139007053, "lat": 45.0570287, "lon": 7.6153429}, {"type": "node", "id": 12139007054, "lat": 45.0575003, "lon": 7.6147831}, {"type": "node", "id": 12139007055, "lat": 45.0557599, "lon": 7.6154007}, {"type": "node", "id": 12139007056, "lat": 45.0564616, "lon": 7.6148329}, {"type": "node", "id": 12139007057, "lat": 45.0580936, "lon": 7.6153087}, {"type": "node", "id": 12139007058, "lat": 45.0586428, "lon": 7.6149047}, {"type": "node", "id": 12139007059, "lat": 45.0586384, "lon": 7.614894}, {"type": "node", "id": 12139007060, "lat": 45.0584801, "lon": 7.6147485}, {"type": "node", "id": 12139128590, "lat": 45.0606061, "lon": 7.6221322}, {"type": "node", "id": 12194813100, "lat": 45.0595713, "lon": 7.6142917}, {"type": "way", "id": 26620384, "nodes": [291981327, 12111135781, 2856450890, 968139361], "tags": {"bridge": "yes", "highway": "tertiary", "lanes": "1", "layer": "1", "lit": "yes", "maxspeed": "50", "name": "Strada Antica di Grugliasco", "oneway": "yes", "parking:both:restriction": "no_parking", "surface": "asphalt"}}, {"type": "way", "id": 37532479, "nodes": [291981317, 480309914, 12111135787, 2856453139, 12111135788, 950728322, 2856453138, 12111135789, 480309868], "tags": {"highway": "tertiary", "lanes": "1", "lit": "yes", "maxspeed": "50", "name": "Strada Antica di Grugliasco", "oneway": "yes", "parking:both:restriction": "no_parking", "surface": "asphalt"}}, {"type": "way", "id": 38320027, "nodes": [452435004, 1668523683], "tags": {"bridge": "yes", "highway": "tertiary", "lanes": "2", "layer": "1", "maxspeed": "50", "name": "Strada Antica di Grugliasco", "surface": "asphalt"}}, {"type": "way", "id": 39537950, "nodes": [475832798, 1194126701, 8942625422, 475832672], "tags": {"highway": "residential", "lanes": "2", "name": "Via Erminio Macario", "name:etymology:wikidata": "Q556400", "oneway": "yes", "surface": "asphalt"}}, {"type": "way", "id": 39685725, "nodes": [4353790039, 2879618070, 4914464895, 534251218, 968139241, 475832793], "tags": {"highway": "unclassified", "name": "Via Marzabotto", "oneway": "yes", "surface": "asphalt"}}, {"type": "way", "id": 39685726, "nodes": [475832795, 475832796], "tags": {"bridge": "yes", "highway": "unclassified", "layer": "1", "name": "Via Alessandro Manzoni", "name:etymology:wikidata": "Q1064", "oneway": "yes", "surface": "asphalt"}}, {"type": "way", "id": 39685727, "nodes": [475832796, 802216522, 8942625424, 475832798], "tags": {"highway": "unclassified", "name": "Via Alessandro Manzoni", "name:etymology:wikidata": "Q1064", "oneway": "yes", "surface": "asphalt"}}, {"type": "way", "id": 39977259, "nodes": [480309865, 1270518277, 6297083392, 6393899006, 10271874940, 10271874915, 10271874942, 10271830480, 10271830481, 480309873], "tags": {"cycleway:both": "no", "highway": "residential", "lanes": "2", "maxspeed": "50", "name": "Via Giuseppe Di Vittorio", "sidewalk": "no", "surface": "asphalt"}}, {"type": "way", "id": 39977260, "nodes": [480309871, 10229303075, 8040903296, 8040903290, 480309877, 10229303071, 480309880, 10229303065, 480309883, 10229303064, 10229303067, 480309938, 8040903289, 480309874], "tags": {"cycleway:both": "no", "highway": "residential", "lanes": "2", "name": "Via Vittorio Alfieri", "sidewalk": "left", "surface": "asphalt"}}, {"type": "way", "id": 39977261, "nodes": [480309874, 480309935, 7940000003, 10271874914, 8066692022, 1436708412], "tags": {"cycleway:both": "no", "highway": "residential", "lanes": "1", "maxspeed": "50", "name": "Via Giuseppe Di Vittorio", "oneway": "yes", "sidewalk": "right", "sidewalk:right:surface": "asphalt", "surface": "asphalt"}}, {"type": "way", "id": 39977268, "nodes": [480309894, 8040903302, 10229303061, 480309895, 10229303062, 8040903301, 8040903298, 10229303060, 480309897, 10229303059, 8040903300, 8040903295, 10229303058, 480309898, 10229303057, 10229303056, 8040903293, 10229303054, 480309900], "tags": {"cycleway:both": "no", "highway": "residential", "lit": "yes", "name": "Via Somalia", "surface": "asphalt"}}, {"type": "way", "id": 39977270, "nodes": [480309868, 2856453137, 950728438, 12111135786, 950728418, 12111135785, 480309911], "tags": {"cycleway:right": "no", "highway": "tertiary", "lanes": "1", "lit": "yes", "maxspeed": "50", "name": "Strada Antica di Grugliasco", "oneway": "yes", "parking:both:restriction": "no_parking", "surface": "asphalt"}}, {"type": "way", "id": 39977271, "nodes": [480309912, 12111135777, 950728423, 1270518311, 12194813100], "tags": {"cycleway:right": "no", "highway": "tertiary", "lanes": "1", "lit": "yes", "maxspeed": "50", "name": "Strada Antica di Grugliasco", "oneway": "yes", "parking:both:restriction": "no_parking", "surface": "asphalt"}}, {"type": "way", "id": 39977272, "nodes": [480309868, 12111135790, 11633780516, 480309906, 4362729375, 6297087353, 6297087354, 4353790054, 6297087355, 2856453140, 480309865], "tags": {"highway": "tertiary", "lanes": "4", "lit": "yes", "maxspeed": "50", "name": "Strada Antica di Grugliasco", "sidewalk:left": "no", "sidewalk:right": "separate", "surface": "asphalt"}}, {"type": "way", "id": 39977273, "nodes": [3088265534, 480309919, 8942485669, 480309920, 8942485670, 480309922, 480309924, 8942485671, 12139007058], "tags": {"highway": "unclassified", "lanes": "2", "lit": "yes", "maxspeed": "50", "maxspeed:type": "sign", "name": "Via Crea", "oneway": "yes", "parking:both:restriction": "no_stopping", "surface": "asphalt"}}, {"type": "way", "id": 39977274, "nodes": [480309938, 10229303069, 10229303068, 480309933, 8040903288, 6297083388, 480309935], "tags": {"cycleway:right": "no", "highway": "residential", "lanes": "1", "name": "Via Vittorio Alfieri", "oneway": "yes", "surface": "asphalt"}}, {"type": "way", "id": 39977276, "nodes": [480309875, 1270518270, 6297083390, 480309941], "tags": {"highway": "tertiary", "lanes": "4", "lit": "yes", "maxspeed": "50", "name": "Corso Tirreno", "sidewalk": "right", "sidewalk:right:surface": "paving_stones", "surface": "asphalt"}}, {"type": "way", "id": 42720161, "nodes": [475832793, 534251216, 475832795], "tags": {"highway": "unclassified", "name": "Via Alessandro Manzoni", "name:etymology:wikidata": "Q1064", "oneway": "yes", "surface": "asphalt"}}, {"type": "way", "id": 42720162, "nodes": [534251216, 534251219, 1493709560, 12111135775, 1842990922], "tags": {"highway": "unclassified", "lit": "yes", "name": "Via Dante Alighieri", "name:etymology:wikidata": "Q1067", "oneway": "yes", "surface": "asphalt"}}, {"type": "way", "id": 42720163, "nodes": [534251218, 534251219], "tags": {"highway": "unclassified", "name": "Via Ugo Foscolo", "name:etymology:wikidata": "Q166234", "surface": "asphalt"}}, {"type": "way", "id": 43205235, "nodes": [541515106, 10229345833, 7105685473, 8137404136, 558294551, 958410762, 7724324784, 541515108], "tags": {"highway": "residential", "maxspeed": "30", "name": "Via Bard", "source:maxspeed": "sign", "surface": "asphalt"}}, {"type": "way", "id": 43205336, "nodes": [541530839, 8072412144, 958410784, 10229345821, 958410782, 2016906738, 741081228, 541541115, 1627688859, 741081242, 1627688857, 541541120, 8072412140, 5726776748, 5726776747, 541541124, 541541129], "tags": {"cycleway:both": "no", "highway": "residential", "name": "Strada Antica di Grugliasco", "surface": "asphalt"}}, {"type": "way", "id": 43903921, "nodes": [558294551, 8072412151, 10229345831, 10229345832, 954620513, 11897185463, 8072412147, 558304678], "tags": {"highway": "residential", "name": "Via Brissogne"}}, {"type": "way", "id": 81563077, "nodes": [968066889, 968066921], "tags": {"cycleway:right": "no", "highway": "tertiary", "lanes": "3", "lanes:psv": "1", "lit": "yes", "maxspeed": "50", "maxspeed:type": "sign", "name": "Via Crea", "oneway": "yes", "psv:lanes": "yes|yes|designated", "sidewalk": "right", "surface": "asphalt"}}, {"type": "way", "id": 81892451, "nodes": [954620516, 12110259110, 7105685475, 11897183149, 11897183146, 8072412150, 954620513], "tags": {"cycleway:both": "no", "highway": "residential", "lit": "yes", "maxspeed": "30", "name": "Via Ozieri", "sidewalk": "both", "source:maxspeed": "sign", "surface": "asphalt"}}, {"type": "way", "id": 82295503, "nodes": [958410780, 4160817556, 7724324783, 958410785, 8072412154, 958410758], "tags": {"highway": "residential", "name": "Via Challant", "surface": "asphalt"}}, {"type": "way", "id": 82295504, "nodes": [958410785, 8072412153, 11897185464, 8072412157, 958410769], "tags": {"highway": "residential", "name": "Via Bionaz", "surface": "asphalt"}}, {"type": "way", "id": 83196471, "nodes": [968066889, 968066859, 8942485664, 968066932, 8942485665, 8942485666, 968066884, 8942485667, 968066949, 8942485668, 968066899, 968066966], "tags": {"highway": "unclassified", "lit": "yes", "maxspeed": "50", "maxspeed:type": "sign", "name": "Via Crea", "oneway": "yes", "parking:both:restriction": "no_stopping", "surface": "asphalt"}}, {"type": "way", "id": 83196483, "nodes": [968066995, 968066916, 8942485659, 968066893, 8942485660, 968066960, 8942485661, 8942485662, 968066910, 8942485663, 968066977, 968066921], "tags": {"cycleway:right": "no", "highway": "unclassified", "lit": "yes", "maxspeed": "50", "maxspeed:type": "sign", "name": "Via Crea", "oneway": "yes", "parking:both:restriction": "no_stopping", "surface": "asphalt"}}, {"type": "way", "id": 107309867, "nodes": [10137579535, 8072412146, 2318240819, 541516400, 541516394, 541530839], "tags": {"highway": "residential", "name": "Via La Thuile", "surface": "asphalt"}}, {"type": "way", "id": 107309874, "nodes": [558304678, 8072412149, 958410769, 4160817560, 558304694], "tags": {"highway": "residential", "name": "Via Bionaz", "surface": "asphalt"}}, {"type": "way", "id": 111995455, "nodes": [480309873, 10271830492, 8040903310, 6393899001, 10271874911, 10229303076, 480309890, 8040903287, 6297083386, 1270518298, 446193210], "tags": {"cycleway:both": "no", "highway": "residential", "lanes": "2", "maxspeed": "50", "name": "Via Giuseppe Di Vittorio", "sidewalk": "both", "sidewalk:both:surface": "asphalt", "surface": "asphalt"}}, {"type": "way", "id": 111995460, "nodes": [480309865, 480309875], "tags": {"highway": "tertiary", "lanes": "4", "lit": "yes", "maxspeed": "50", "name": "Strada Antica di Grugliasco", "sidewalk:left": "no", "sidewalk:right": "separate", "surface": "asphalt"}}, {"type": "way", "id": 111995471, "nodes": [12139007053, 12139007057], "tags": {"highway": "tertiary", "lanes": "3", "lit": "yes", "maxspeed": "50", "maxspeed:type": "sign", "name": "Via Crea", "oneway": "yes", "sidewalk:right": "separate", "surface": "asphalt"}}, {"type": "way", "id": 111995477, "nodes": [480309911, 950728386, 12111135792, 291981320, 3088265531, 480309912], "tags": {"cycleway:right": "no", "highway": "tertiary", "junction": "roundabout", "lanes": "2", "lit": "yes", "maxspeed": "50", "parking:both:restriction": "no_stopping", "surface": "asphalt"}}, {"type": "way", "id": 111995482, "nodes": [480309874, 480309873], "tags": {"cycleway:both": "no", "highway": "residential", "lanes": "2", "name": "Via Vittorio Alfieri", "sidewalk": "left", "surface": "asphalt"}}, {"type": "way", "id": 130443664, "nodes": [1436708412, 480309940, 6297083391, 1270518312, 480309875], "tags": {"highway": "residential", "lane_markings": "no", "maxspeed": "50", "name": "Via Giuseppe Di Vittorio", "oneway": "yes", "sidewalk": "right", "sidewalk:right:surface": "asphalt", "surface": "asphalt"}}, {"type": "way", "id": 135016482, "nodes": [958410758, 10229345830, 10229345829, 8072412156, 958410762], "tags": {"highway": "residential", "name": "Via Bard", "surface": "asphalt"}}, {"type": "way", "id": 135016488, "nodes": [541515108, 958410780, 4160817555, 6438403802, 11897188944, 11897188947, 4160817559, 558304694, 10229345827, 2318240818, 541516400, 10229345828, 1631841304, 10229345836, 2318240816, 12139128590], "tags": {"bicycle": "yes", "cycleway": "no", "foot": "yes", "highway": "residential", "name": "Via Challant", "oneway": "no", "sidewalk": "left", "surface": "asphalt"}}, {"type": "way", "id": 149822413, "nodes": [8059293110, 8375944293, 1627688876, 10152582758, 9580741275, 1627688864, 1627688858], "tags": {"highway": "residential", "lit": "no", "maxspeed": "30", "name": "Via Teresa Mattei", "source:maxspeed": "IT:urban", "surface": "fine_gravel"}}, {"type": "way", "id": 154296737, "nodes": [1668523683, 1668523680], "tags": {"highway": "tertiary", "lanes": "2", "maxspeed": "50", "name": "Strada Antica di Grugliasco", "surface": "asphalt"}}, {"type": "way", "id": 154296739, "nodes": [1668523680, 291981327], "tags": {"bridge": "yes", "highway": "tertiary", "lanes": "2", "layer": "1", "maxspeed": "50", "name": "Strada Antica di Grugliasco", "surface": "asphalt"}}, {"type": "way", "id": 154296766, "nodes": [802216531, 9288504122, 802216525, 1668523677, 8942625423, 802216522], "tags": {"cycleway:right": "no", "highway": "residential", "name": "Strada Campagnola", "oneway": "yes", "surface": "asphalt"}}, {"type": "way", "id": 191108891, "nodes": [2016906740, 2016906738], "tags": {"bicycle": "yes", "cycleway:both": "no", "foot": "yes", "highway": "residential", "name": "Via Cassinelli", "sidewalk": "right", "surface": "asphalt"}}, {"type": "way", "id": 644332361, "nodes": [1842990922, 4353790038, 1849617217, 452435004], "tags": {"highway": "tertiary", "lanes": "2", "lit": "yes", "maxspeed": "50", "name": "Strada Antica di Grugliasco", "surface": "asphalt"}}, {"type": "way", "id": 686854530, "nodes": [6438403802, 6438403803, 6438403804], "tags": {"highway": "residential", "surface": "asphalt"}}, {"type": "way", "id": 749296446, "nodes": [480309912, 12111135778, 291981322, 12111135779, 289047986, 12111135780, 950728470, 291981323], "tags": {"cycleway:right": "no", "highway": "tertiary", "junction": "roundabout", "lanes": "2", "lit": "yes", "maxspeed": "50", "parking:both:restriction": "no_stopping", "surface": "asphalt"}}, {"type": "way", "id": 749296447, "nodes": [291981317, 291981319, 3088265533, 480309911], "tags": {"highway": "tertiary", "junction": "roundabout", "lanes": "2", "lit": "yes", "maxspeed": "50", "parking:both:restriction": "no_stopping", "surface": "asphalt"}}, {"type": "way", "id": 749296457, "nodes": [291981323, 1478247990, 473708976, 1478247973, 291981325], "tags": {"highway": "tertiary", "junction": "roundabout", "lanes": "2", "lit": "yes", "maxspeed": "50", "parking:both:restriction": "no_stopping", "surface": "asphalt"}}, {"type": "way", "id": 827371144, "nodes": [7724324784, 8072412152, 8072412155, 7724324783], "tags": {"highway": "residential", "name": "Via Challant", "surface": "asphalt"}}, {"type": "way", "id": 834003033, "nodes": [291981325, 480309908, 950728371, 12111135791, 3088265532, 291981315], "tags": {"cycleway:right": "no", "highway": "tertiary", "junction": "roundabout", "lanes": "2", "lit": "yes", "maxspeed": "50", "parking:both:restriction": "no_stopping", "surface": "asphalt"}}, {"type": "way", "id": 834003034, "nodes": [291981315, 480309909, 1270518308, 12111135784, 291981317], "tags": {"highway": "tertiary", "junction": "roundabout", "lanes": "2", "lit": "yes", "maxspeed": "50", "parking:both:restriction": "no_stopping", "surface": "asphalt"}}, {"type": "way", "id": 1307818975, "nodes": [12111135768, 4353790039], "tags": {"highway": "tertiary", "lanes": "2", "lit": "yes", "maxspeed": "50", "name": "Strada Antica di Grugliasco", "surface": "asphalt"}}, {"type": "way", "id": 1307818976, "nodes": [4353790039, 12111135773], "tags": {"highway": "tertiary", "lanes": "3", "lanes:backward": "2", "lanes:forward": "1", "lit": "yes", "maxspeed": "50", "name": "Strada Antica di Grugliasco", "surface": "asphalt", "turn:lanes:backward": "left|through"}}, {"type": "way", "id": 1307818977, "nodes": [12111135774, 1842990922], "tags": {"highway": "tertiary", "lanes": "3", "lanes:backward": "2", "lanes:forward": "1", "lit": "yes", "maxspeed": "50", "name": "Strada Antica di Grugliasco", "surface": "asphalt", "turn:lanes:backward": "merge_to_right|through"}}, {"type": "way", "id": 1307818978, "nodes": [12111135773, 12111135774], "tags": {"highway": "tertiary", "lanes": "2", "lit": "yes", "maxspeed": "50", "name": "Strada Antica di Grugliasco", "surface": "asphalt"}}, {"type": "way", "id": 1307818979, "nodes": [480309941, 12111135794], "tags": {"cycleway:both": "no", "highway": "tertiary", "lanes": "4", "lit": "yes", "maxspeed": "50", "name": "Corso Tirreno", "sidewalk": "right", "sidewalk:right:surface": "paving_stones", "surface": "asphalt"}}, {"type": "way", "id": 1311408672, "nodes": [291981325, 1270518252, 480309929, 3088265535], "tags": {"cycleway:right": "no", "highway": "tertiary", "lanes": "1", "lit": "yes", "maxspeed": "50", "maxspeed:type": "sign", "name": "Via Crea", "oneway": "yes", "sidewalk": "right", "surface": "asphalt"}}, {"type": "way", "id": 1311408673, "nodes": [12139007042, 473708950, 12139007047], "tags": {"cycleway:right": "no", "highway": "tertiary", "lanes": "3", "lanes:psv": "1", "lit": "yes", "maxspeed": "50", "maxspeed:type": "sign", "name": "Via Crea", "oneway": "yes", "psv:lanes": "yes|yes|designated", "sidewalk": "right", "surface": "asphalt"}}, {"type": "way", "id": 1311408674, "nodes": [968066921, 12139007042], "tags": {"cycleway:right": "no", "highway": "tertiary", "lanes": "4", "lit": "yes", "maxspeed": "50", "maxspeed:type": "sign", "name": "Via Crea", "oneway": "yes", "sidewalk": "right", "surface": "asphalt", "turn:lanes:forward": "merge_to_left|none|none|none"}}, {"type": "way", "id": 1311408676, "nodes": [1194057653, 8942485674, 12139007054], "tags": {"cycleway:right": "no", "highway": "tertiary", "lanes": "3", "lanes:psv": "1", "lit": "yes", "maxspeed": "50", "maxspeed:type": "sign", "name": "Via Crea", "oneway": "yes", "psv:lanes": "yes|yes|designated", "sidewalk": "right", "surface": "asphalt"}}, {"type": "way", "id": 1311408677, "nodes": [12139007045, 8040903316, 12139007046], "tags": {"change:lanes": "no|no|no", "cycleway:right": "no", "highway": "tertiary", "lanes": "3", "lanes:psv": "1", "lit": "yes", "maxspeed": "50", "maxspeed:type": "sign", "name": "Via Crea", "oneway": "yes", "psv:lanes": "yes|yes|designated", "sidewalk": "right", "surface": "asphalt"}}, {"type": "way", "id": 1311408678, "nodes": [12139007048, 8040903312, 12139007044, 968066907], "tags": {"cycleway:right": "no", "highway": "tertiary", "lanes": "3", "lanes:psv": "1", "lit": "yes", "maxspeed": "50", "maxspeed:type": "sign", "name": "Via Crea", "oneway": "yes", "psv:lanes": "yes|yes|designated", "sidewalk": "right", "surface": "asphalt"}}, {"type": "way", "id": 1311408679, "nodes": [12139007047, 12139007048], "tags": {"change:lanes": "no|no|no", "cycleway:right": "no", "highway": "tertiary", "lanes": "3", "lanes:psv": "1", "lit": "yes", "maxspeed": "50", "maxspeed:type": "sign", "name": "Via Crea", "oneway": "yes", "psv:lanes": "yes|yes|designated", "sidewalk": "right", "surface": "asphalt"}}, {"type": "way", "id": 1311408680, "nodes": [291981313, 6315013294, 968066887, 8040903311, 12139007049], "tags": {"highway": "tertiary", "lanes": "3", "lit": "yes", "maxspeed": "50", "maxspeed:type": "sign", "name": "Via Crea", "oneway": "yes", "sidewalk:right": "separate", "surface": "asphalt"}}, {"type": "way", "id": 1311408681, "nodes": [12139007049, 968066903], "tags": {"highway": "tertiary", "lanes": "4", "lit": "yes", "maxspeed": "50", "maxspeed:type": "sign", "name": "Via Crea", "oneway": "yes", "sidewalk:right": "separate", "surface": "asphalt", "turn:lanes:forward": "left|through|through|through"}}, {"type": "way", "id": 1311408682, "nodes": [968066995, 968066966, 968066996], "tags": {"highway": "tertiary", "lanes": "3", "lit": "yes", "maxspeed": "50", "maxspeed:type": "sign", "name": "Via Crea", "oneway": "yes", "sidewalk:right": "separate", "surface": "asphalt"}}, {"type": "way", "id": 1311408683, "nodes": [968066996, 12139007052], "tags": {"highway": "tertiary", "lanes": "4", "lit": "yes", "maxspeed": "50", "maxspeed:type": "sign", "name": "Via Crea", "oneway": "yes", "sidewalk:right": "separate", "surface": "asphalt", "turn:lanes:forward": "merge_to_left|through|through|through"}}, {"type": "way", "id": 1311408684, "nodes": [12139007052, 8040903317, 12139007053], "tags": {"change:lanes": "no|no|no", "highway": "tertiary", "lanes": "3", "lit": "yes", "maxspeed": "50", "maxspeed:type": "sign", "name": "Via Crea", "oneway": "yes", "sidewalk:right": "separate", "surface": "asphalt"}}, {"type": "way", "id": 1311408685, "nodes": [12139007054, 289048006], "tags": {"cycleway:right": "no", "highway": "tertiary", "lanes": "4", "lanes:psv": "1", "lit": "yes", "maxspeed": "50", "maxspeed:type": "sign", "name": "Via Crea", "oneway": "yes", "psv:lanes": "yes|yes|designated", "sidewalk": "right", "surface": "asphalt", "turn:lanes:forward": "left|through|through|through"}}, {"type": "way", "id": 1311408686, "nodes": [289048006, 12139007045], "tags": {"cycleway:right": "no", "highway": "tertiary", "lanes": "3", "lanes:psv": "1", "lit": "yes", "maxspeed": "50", "maxspeed:type": "sign", "name": "Via Crea", "oneway": "yes", "psv:lanes": "yes|yes|designated", "sidewalk": "right", "surface": "asphalt"}}, {"type": "way", "id": 1311408687, "nodes": [968066903, 12139007055], "tags": {"highway": "tertiary", "lanes": "3", "lit": "yes", "maxspeed": "50", "maxspeed:type": "sign", "name": "Via Crea", "oneway": "yes", "sidewalk:right": "separate", "surface": "asphalt"}}, {"type": "way", "id": 1311408688, "nodes": [12139007055, 968066995], "tags": {"highway": "tertiary", "lanes": "4", "lit": "yes", "maxspeed": "50", "maxspeed:type": "sign", "name": "Via Crea", "oneway": "yes", "sidewalk:right": "separate", "surface": "asphalt", "turn:lanes:forward": "left|through|through|through"}}, {"type": "way", "id": 1311408689, "nodes": [12139007046, 8942485687, 12139007056], "tags": {"cycleway:right": "no", "highway": "tertiary", "lanes": "3", "lanes:psv": "1", "lit": "yes", "maxspeed": "50", "maxspeed:type": "sign", "name": "Via Crea", "oneway": "yes", "psv:lanes": "yes|yes|designated", "sidewalk": "right", "surface": "asphalt"}}, {"type": "way", "id": 1311408690, "nodes": [12139007056, 968066889], "tags": {"cycleway:right": "no", "highway": "tertiary", "lanes": "4", "lanes:psv": "1", "lit": "yes", "maxspeed": "50", "maxspeed:type": "sign", "name": "Via Crea", "oneway": "yes", "psv:lanes": "yes|yes|designated", "sidewalk": "right", "surface": "asphalt", "turn:lanes:forward": "left|through|through|through"}}, {"type": "way", "id": 1311408691, "nodes": [3088265534, 480309917, 1270518269, 12111135783, 291981315], "tags": {"highway": "tertiary", "lanes": "2", "lit": "yes", "maxspeed": "50", "maxspeed:type": "sign", "name": "Via Crea", "oneway": "yes", "sidewalk:right": "separate", "surface": "asphalt"}}, {"type": "way", "id": 1311408692, "nodes": [12139007057, 3088265534], "tags": {"highway": "tertiary", "lanes": "3", "lit": "yes", "maxspeed": "50", "maxspeed:type": "sign", "name": "Via Crea", "oneway": "yes", "sidewalk:right": "separate", "surface": "asphalt", "turn:lanes": "left|through|through"}}, {"type": "way", "id": 1311408693, "nodes": [3088265535, 1194057653], "tags": {"cycleway:right": "no", "highway": "tertiary", "lanes": "3", "lit": "yes", "maxspeed": "50", "maxspeed:type": "sign", "name": "Via Crea", "oneway": "yes", "sidewalk": "right", "surface": "asphalt"}}, {"type": "way", "id": 1311408694, "nodes": [12139007058, 12139007059, 480309926, 480309927, 8942485673, 8942485672, 12139007060, 3088265535], "tags": {"change:lanes": "no|no", "highway": "unclassified", "lanes": "2", "lit": "yes", "maxspeed": "50", "maxspeed:type": "sign", "name": "Via Crea", "oneway": "yes", "parking:both:restriction": "no_stopping", "surface": "asphalt"}}, {"type": "way", "id": 1317609787, "nodes": [12194813100, 2856450889, 12111135782, 291981327], "tags": {"bridge": "yes", "cycleway:right": "no", "highway": "tertiary", "lanes": "1", "layer": "1", "lit": "yes", "maxspeed": "50", "name": "Strada Antica di Grugliasco", "oneway": "yes", "parking:both:restriction": "no_parking", "surface": "asphalt"}}, {"type": "way", "id": 1317609788, "nodes": [968139361, 1270518263, 480309915, 12111135776, 291981323], "tags": {"highway": "tertiary", "lanes": "1", "lit": "yes", "maxspeed": "50", "name": "Strada Antica di Grugliasco", "oneway": "yes", "parking:both:restriction": "no_parking", "surface": "asphalt"}}]}